odoo/addons/odoo_cron_patch/__init__.py
odoo/addons/odoo_cron_patch/__manifest__.py
odoo/addons/odoo_cron_patch/auto_load.py
odoo/addons/odoo_cron_patch/cron_patch.py
mangono_addon_odoo_cron_patch-0.1.1.dist-info/METADATA
mangono_addon_odoo_cron_patch-0.1.1.dist-info/WHEEL
mangono_addon_odoo_cron_patch-0.1.1.dist-info/entry_points.txt
mangono_addon_odoo_cron_patch-0.1.1.dist-info/top_level.txt
mangono_addon_odoo_cron_patch-0.1.1.dist-info/RECORD
